README.md
setup.py
exch_rate/__init__.py
exch_rate/exch_rate.py
exch_rate.egg-info/PKG-INFO
exch_rate.egg-info/SOURCES.txt
exch_rate.egg-info/dependency_links.txt
exch_rate.egg-info/entry_points.txt
exch_rate.egg-info/requires.txt
exch_rate.egg-info/top_level.txt