Metadata-Version: 1.0
Name: exch-rate
Version: 0.2
Summary: Tool to fetch exchange rates and convert foreign currencies.
Home-page: https://github.com/prahladyeri/exch-rate
Author: Prahlad Yeri
Author-email: prahladyeri@yahoo.com
License: MIT
Platform: UNKNOWN
